{
    "title": "Build a simple Angular application",
    "description": "aim november 2022",
    "details": {
        "intro": {
            "text": "01start.md"
        },
        "steps": [
            {
                "text": "02step1.md"
            },
            {
                "text": "03step2.md"
            },
            {
                "text": "04step3.md"
            }
        ],
        "finish": {
            "text": "05end.md"
        }
    },
    "backend": {
        "imageid": "ubuntu"
    }
}